setup.py
slackup/__init__.py
slackup/slackup
slackup.egg-info/PKG-INFO
slackup.egg-info/SOURCES.txt
slackup.egg-info/dependency_links.txt
slackup.egg-info/requires.txt
slackup.egg-info/top_level.txt