Metadata-Version: 1.0
Name: slackup
Version: 0.0
Summary: A tool for uploading files to Slack from the command line.
Home-page: UNKNOWN
Author: Rock Kitchen Harris
Author-email: UNKNOWN
License: UNKNOWN
Platform: UNKNOWN
